dots/__init__.py
dots/cli.py
dots/desktop.py
dots/shell.py
dots/tui.py
dots/tests/__init__.py
dots_linux-0.0.1.dist-info/DESCRIPTION.rst
dots_linux-0.0.1.dist-info/METADATA
dots_linux-0.0.1.dist-info/RECORD
dots_linux-0.0.1.dist-info/WHEEL
dots_linux-0.0.1.dist-info/entry_points.txt
dots_linux-0.0.1.dist-info/metadata.json
dots_linux-0.0.1.dist-info/top_level.txt
tests/__init__.py
tests/test_tui.py
