Metadata-Version: 2.0
Name: dots-linux
Version: 0.0.1
Summary: Linux System Manager.
Home-page: https://github.com/hoytnix/dots
Author: Michael Hoyt
Author-email: dots@hoyt.io
License: MIT
Platform: UNKNOWN
Classifier: Development Status :: 1 - Planning
Classifier: Environment :: Console
Classifier: Intended Audience :: End Users/Desktop
Classifier: License :: OSI Approved :: MIT License
Classifier: Natural Language :: English
Classifier: Operating System :: POSIX :: Linux
Classifier: Programming Language :: Python :: 3.5
Classifier: Programming Language :: Unix Shell
Classifier: Topic :: Desktop Environment
Classifier: Topic :: System :: Boot :: Init
Classifier: Topic :: System :: Installation/Setup
Classifier: Topic :: Utilities
